[
  {
    "English": "Father",
    "Urdu": "باپ / والد",
    "Hindi": "पिता / बाप",
    "Arabic": "أب / والد"
  },
  {
    "English": "Mother",
    "Urdu": "ماں / والدہ",
    "Hindi": "माँ / माता",
    "Arabic": "أم / والدة"
  },
  {
    "English": "Brother",
    "Urdu": "بھائی / بھائی جان",
    "Hindi": "भाई",
    "Arabic": "أخ / أخي"
  },
  {
    "English": "Sister",
    "Urdu": "بہن / بہن جان",
    "Hindi": "बहन",
    "Arabic": "أخت / أختي"
  },
  {
    "English": "Son",
    "Urdu": "بیٹا / لڑکا",
    "Hindi": "बेटा / लड़का",
    "Arabic": "ابن"
  },
  {
    "English": "Daughter",
    "Urdu": "بیٹی / لڑکی",
    "Hindi": "बेटी / लड़की",
    "Arabic": "بنت"
  },
  {
    "English": "Grandfather",
    "Urdu": "دادا / نانا / دادو / ننوا / دادا جان / نانا جان",
    "Hindi": "दादा / नाना / दादाजी / नानाजी / दादा / नाना",
    "Arabic": "جد / جدي / أجداد / أجدادي"
  },
  {
    "English": "Grandmother",
    "Urdu": "دادی / نانی / دادی جان / نانی جان",
    "Hindi": "दादी / नानी / दादीमाँ / नानीमाँ",
    "Arabic": "جدة / جدتي / جدات / أجداد / أجدادي"
  },
  {
    "English": "Grandson",
    "Urdu": "پوتا / نواز",
    "Hindi": "पोता / नतीजा",
    "Arabic": "حفيد / حفيدي"
  },
  {
    "English": "Granddaughter",
    "Urdu": "پوتڑی / نواسی",
    "Hindi": "पोती / नतीजी",
    "Arabic": "حفيدة / حفيدتي"
  },
  {
    "English": "Uncle (paternal)",
    "Urdu": "چچا / خالا / ماموں",
    "Hindi": "चाचा / खाला / मामू",
    "Arabic": "عم / خال / عمي / خالي"
  },
  {
    "English": "Aunt (paternal)",
    "Urdu": "چچی / خالہ / مامونی",
    "Hindi": "चाची / खाला / मामी",
    "Arabic": "عمة / خالة / عمة / خالتي"
  },
  {
    "English": "Uncle (maternal)",
    "Urdu": "ماما / مومنا",
    "Hindi": "मामा / मौसा / मोमिना",
    "Arabic": "عم / عمو / عمي / عمتي"
  },
  {
    "English": "Aunt (maternal)",
    "Urdu": "مامی / مامونی",
    "Hindi": "मामी / मौसी / मोमिनी",
    "Arabic": "عمة / عمتي / خالة / خالتي"
  },
  {
    "English": "Cousin (male)",
    "Urdu": "چھوٹا باچہ / کچا بھائی / بھائی کا بیٹا / بھائی جیسا",
    "Hindi": "भाईजान / भाई का बेटा / छोटा भाई",
    "Arabic": "ابن عم /"
  }
]
